secyan_python.cpython-36m-darwin.so
secyan_python-0.3.7.dist-info/METADATA
secyan_python-0.3.7.dist-info/WHEEL
secyan_python-0.3.7.dist-info/top_level.txt
secyan_python-0.3.7.dist-info/RECORD
