Metadata-Version: 2.1
Name: secyan_python
Version: 0.3.7
Summary: SECYAN c++ implementation
Home-page: UNKNOWN
Author: Qiwei Li
Author-email: sirily1997@gmail.com
License: UNKNOWN
Platform: any
Classifier: Programming Language :: Python :: 3.6
Classifier: Programming Language :: Python :: 3.7
Classifier: Programming Language :: Python :: 3.8
Classifier: Programming Language :: Python :: 3.9
Requires-Python: >=3.6
